{
  "updatedAt": "2026-05-24 13:39",
  "matches": [
    {
      "kickoffUTC": "2026-05-24T13:00:00Z",
      "home": "Parma",
      "away": "Sassuolo",
      "league": "Serie A",
      "lClass": "l-serie",
      "japanese": [],
      "national": false
    },
    {
      "kickoffUTC": "2026-05-24T15:00:00Z",
      "home": "Sunderland",
      "away": "Chelsea",
      "league": "EPL",
      "lClass": "l-epl",
      "japanese": [],
      "national": false
    },
    {
      "kickoffUTC": "2026-05-24T15:00:00Z",
      "home": "Man City",
      "away": "Aston Villa",
      "league": "EPL",
      "lClass": "l-epl",
      "japanese": [],
      "national": false
    },
    {
      "kickoffUTC": "2026-05-24T15:00:00Z",
      "home": "Crystal Palace",
      "away": "Arsenal",
      "league": "EPL",
      "lClass": "l-epl",
      "japanese": [],
      "national": false
    },
    {
      "kickoffUTC": "2026-05-24T15:00:00Z",
      "home": "Tottenham",
      "away": "Everton",
      "league": "EPL",
      "lClass": "l-epl",
      "japanese": [],
      "national": false
    },
    {
      "kickoffUTC": "2026-05-24T15:00:00Z",
      "home": "Fulham",
      "away": "Newcastle",
      "league": "EPL",
      "lClass": "l-epl",
      "japanese": [],
      "national": false
    },
    {
      "kickoffUTC": "2026-05-24T15:00:00Z",
      "home": "Brighton Hove",
      "away": "Man United",
      "league": "EPL",
      "lClass": "l-epl",
      "japanese": [
        "三笘薫"
      ],
      "national": false
    },
    {
      "kickoffUTC": "2026-05-24T15:00:00Z",
      "home": "Nottingham",
      "away": "Bournemouth",
      "league": "EPL",
      "lClass": "l-epl",
      "japanese": [],
      "national": false
    },
    {
      "kickoffUTC": "2026-05-24T15:00:00Z",
      "home": "Burnley",
      "away": "Wolverhampton",
      "league": "EPL",
      "lClass": "l-epl",
      "japanese": [],
      "national": false
    },
    {
      "kickoffUTC": "2026-05-24T15:00:00Z",
      "home": "West Ham",
      "away": "Leeds United",
      "league": "EPL",
      "lClass": "l-epl",
      "japanese": [],
      "national": false
    },
    {
      "kickoffUTC": "2026-05-24T15:00:00Z",
      "home": "Liverpool",
      "away": "Brentford",
      "league": "EPL",
      "lClass": "l-epl",
      "japanese": [
        "遠藤航"
      ],
      "national": false
    },
    {
      "kickoffUTC": "2026-05-24T16:00:00Z",
      "home": "Napoli",
      "away": "Udinese",
      "league": "Serie A",
      "lClass": "l-serie",
      "japanese": [],
      "national": false
    },
    {
      "kickoffUTC": "2026-05-24T18:45:00Z",
      "home": "Cremonese",
      "away": "Como 1907",
      "league": "Serie A",
      "lClass": "l-serie",
      "japanese": [],
      "national": false
    },
    {
      "kickoffUTC": "2026-05-24T18:45:00Z",
      "home": "Torino",
      "away": "Juventus",
      "league": "Serie A",
      "lClass": "l-serie",
      "japanese": [],
      "national": false
    },
    {
      "kickoffUTC": "2026-05-24T18:45:00Z",
      "home": "Milan",
      "away": "Cagliari",
      "league": "Serie A",
      "lClass": "l-serie",
      "japanese": [],
      "national": false
    },
    {
      "kickoffUTC": "2026-05-24T18:45:00Z",
      "home": "Lecce",
      "away": "Genoa",
      "league": "Serie A",
      "lClass": "l-serie",
      "japanese": [],
      "national": false
    },
    {
      "kickoffUTC": "2026-05-24T18:45:00Z",
      "home": "Verona",
      "away": "Roma",
      "league": "Serie A",
      "lClass": "l-serie",
      "japanese": [],
      "national": false
    },
    {
      "kickoffUTC": "2026-05-24T19:00:00Z",
      "home": "Villarreal",
      "away": "Atleti",
      "league": "LaLiga",
      "lClass": "l-laliga",
      "japanese": [],
      "national": false
    },
    {
      "kickoffUTC": "2026-05-24T19:00:00Z",
      "home": "Clube do Remo",
      "away": "Paranaense",
      "league": "Brasileirao",
      "lClass": "l-ligap",
      "japanese": [],
      "national": false
    },
    {
      "kickoffUTC": "2026-05-24T19:00:00Z",
      "home": "Cruzeiro",
      "away": "Chapecoense",
      "league": "Brasileirao",
      "lClass": "l-ligap",
      "japanese": [],
      "national": false
    },
    {
      "kickoffUTC": "2026-05-24T21:30:00Z",
      "home": "Corinthians",
      "away": "Mineiro",
      "league": "Brasileirao",
      "lClass": "l-ligap",
      "japanese": [],
      "national": false
    },
    {
      "kickoffUTC": "2026-05-24T23:30:00Z",
      "home": "Vasco da Gama",
      "away": "Bragantino",
      "league": "Brasileirao",
      "lClass": "l-ligap",
      "japanese": [],
      "national": false
    },
    {
      "kickoffUTC": "2026-05-25T23:00:00Z",
      "home": "Coritiba",
      "away": "Bahia",
      "league": "Brasileirao",
      "lClass": "l-ligap",
      "japanese": [],
      "national": false
    },
    {
      "kickoffUTC": "2026-05-26T22:00:00Z",
      "home": "Lanús",
      "away": "Mirassol",
      "league": "Copa Libertadores",
      "lClass": "l-champ",
      "japanese": [],
      "national": false
    },
    {
      "kickoffUTC": "2026-05-26T22:00:00Z",
      "home": "LDU de Quito",
      "away": "Always Ready",
      "league": "Copa Libertadores",
      "lClass": "l-champ",
      "japanese": [],
      "national": false
    },
    {
      "kickoffUTC": "2026-05-27T00:30:00Z",
      "home": "Universitario",
      "away": "Tolima",
      "league": "Copa Libertadores",
      "lClass": "l-champ",
      "japanese": [],
      "national": false
    },
    {
      "kickoffUTC": "2026-05-27T00:30:00Z",
      "home": "Estudiantes LP",
      "away": "Independiente",
      "league": "Copa Libertadores",
      "lClass": "l-champ",
      "japanese": [],
      "national": false
    },
    {
      "kickoffUTC": "2026-05-27T00:30:00Z",
      "home": "Flamengo",
      "away": "Cusco",
      "league": "Copa Libertadores",
      "lClass": "l-champ",
      "japanese": [],
      "national": false
    },
    {
      "kickoffUTC": "2026-05-27T00:30:00Z",
      "home": "Club Nacional",
      "away": "Coquimbo Unido",
      "league": "Copa Libertadores",
      "lClass": "l-champ",
      "japanese": [],
      "national": false
    },
    {
      "kickoffUTC": "2026-05-27T22:00:00Z",
      "home": "Libertad",
      "away": "Universidad Central",
      "league": "Copa Libertadores",
      "lClass": "l-champ",
      "japanese": [],
      "national": false
    },
    {
      "kickoffUTC": "2026-05-27T22:00:00Z",
      "home": "Independiente",
      "away": "Rosario",
      "league": "Copa Libertadores",
      "lClass": "l-champ",
      "japanese": [],
      "national": false
    },
    {
      "kickoffUTC": "2026-05-28T00:30:00Z",
      "home": "Corinthians",
      "away": "Platense",
      "league": "Copa Libertadores",
      "lClass": "l-champ",
      "japanese": [],
      "national": false
    },
    {
      "kickoffUTC": "2026-05-28T00:30:00Z",
      "home": "Club Bolívar",
      "away": "Rivadavia",
      "league": "Copa Libertadores",
      "lClass": "l-champ",
      "japanese": [],
      "national": false
    },
    {
      "kickoffUTC": "2026-05-28T00:30:00Z",
      "home": "Fluminense",
      "away": "La Guaira",
      "league": "Copa Libertadores",
      "lClass": "l-champ",
      "japanese": [],
      "national": false
    },
    {
      "kickoffUTC": "2026-05-28T00:30:00Z",
      "home": "Peñarol",
      "away": "Santa Fe",
      "league": "Copa Libertadores",
      "lClass": "l-champ",
      "japanese": [],
      "national": false
    },
    {
      "kickoffUTC": "2026-05-28T22:00:00Z",
      "home": "Cerro Porteño",
      "away": "Cristal",
      "league": "Copa Libertadores",
      "lClass": "l-champ",
      "japanese": [],
      "national": false
    },
    {
      "kickoffUTC": "2026-05-28T22:00:00Z",
      "home": "Palmeiras",
      "away": "Junior",
      "league": "Copa Libertadores",
      "lClass": "l-champ",
      "japanese": [],
      "national": false
    },
    {
      "kickoffUTC": "2026-05-29T00:30:00Z",
      "home": "Cruzeiro",
      "away": "Barcelona SC",
      "league": "Copa Libertadores",
      "lClass": "l-champ",
      "japanese": [],
      "national": false
    },
    {
      "kickoffUTC": "2026-05-29T00:30:00Z",
      "home": "Boca Juniors",
      "away": "Univ Católica",
      "league": "Copa Libertadores",
      "lClass": "l-champ",
      "japanese": [],
      "national": false
    },
    {
      "kickoffUTC": "2026-05-30T16:00:00Z",
      "home": "PSG",
      "away": "Arsenal",
      "league": "Champions League",
      "lClass": "l-champ",
      "japanese": [],
      "national": false
    },
    {
      "kickoffUTC": "2026-05-30T19:00:00Z",
      "home": "Paranaense",
      "away": "Mirassol",
      "league": "Brasileirao",
      "lClass": "l-ligap",
      "japanese": [],
      "national": false
    },
    {
      "kickoffUTC": "2026-05-30T19:00:00Z",
      "home": "Flamengo",
      "away": "Coritiba",
      "league": "Brasileirao",
      "lClass": "l-ligap",
      "japanese": [],
      "national": false
    },
    {
      "kickoffUTC": "2026-05-30T20:30:00Z",
      "home": "Grêmio",
      "away": "Corinthians",
      "league": "Brasileirao",
      "lClass": "l-ligap",
      "japanese": [],
      "national": false
    },
    {
      "kickoffUTC": "2026-05-30T20:30:00Z",
      "home": "Bahia",
      "away": "Botafogo",
      "league": "Brasileirao",
      "lClass": "l-ligap",
      "japanese": [],
      "national": false
    },
    {
      "kickoffUTC": "2026-05-31T00:00:00Z",
      "home": "Santos",
      "away": "Vitória",
      "league": "Brasileirao",
      "lClass": "l-ligap",
      "japanese": [],
      "national": false
    },
    {
      "kickoffUTC": "2026-05-31T14:00:00Z",
      "home": "Bragantino",
      "away": "Internacional",
      "league": "Brasileirao",
      "lClass": "l-ligap",
      "japanese": [],
      "national": false
    },
    {
      "kickoffUTC": "2026-05-31T19:00:00Z",
      "home": "Vasco da Gama",
      "away": "Mineiro",
      "league": "Brasileirao",
      "lClass": "l-ligap",
      "japanese": [],
      "national": false
    },
    {
      "kickoffUTC": "2026-05-31T19:00:00Z",
      "home": "Palmeiras",
      "away": "Chapecoense",
      "league": "Brasileirao",
      "lClass": "l-ligap",
      "japanese": [],
      "national": false
    },
    {
      "kickoffUTC": "2026-05-31T23:30:00Z",
      "home": "Clube do Remo",
      "away": "São Paulo",
      "league": "Brasileirao",
      "lClass": "l-ligap",
      "japanese": [],
      "national": false
    },
    {
      "kickoffUTC": "2026-05-31T23:30:00Z",
      "home": "Cruzeiro",
      "away": "Fluminense",
      "league": "Brasileirao",
      "lClass": "l-ligap",
      "japanese": [],
      "national": false
    }
  ]
}